smoldot_light/__init__.py
smoldot_light/smoldot_light.cpython-313-darwin.so
smoldot_light-0.1.0.dist-info/METADATA
smoldot_light-0.1.0.dist-info/WHEEL
smoldot_light-0.1.0.dist-info/licenses/LICENSE
smoldot_light-0.1.0.dist-info/RECORD
