Metadata-Version: 2.4
Name: smoldot-light
Version: 0.1.0
Classifier: Programming Language :: Rust
Classifier: Programming Language :: Python :: Implementation :: CPython
Classifier: Programming Language :: Python :: Implementation :: PyPy
License-File: LICENSE
Summary: Python bindings for the smoldot_light Rust crate.
Home-Page: https://github.com/JAMdotTech/py-smoldot-light
Author-email: JAMdot Technologies <devops@jamdot.tech>
Requires-Python: >=3.8
